troller/__init__.py
troller/bot.py
troller/exchange.py
troller/type.py
troller-0.0.1.dist-info/METADATA
troller-0.0.1.dist-info/WHEEL
troller-0.0.1.dist-info/top_level.txt
troller-0.0.1.dist-info/RECORD
