Metadata-Version: 2.1
Name: troller
Version: 0.0.1
Requires-Dist: requests
